quickstats/__init__.py
quickstats/_version.py
quickstats/algorithms/__init__.py
quickstats/algorithms/bump_hunt/__init__.py
quickstats/algorithms/bump_hunt/bump_hunt_1d.py
quickstats/algorithms/bump_hunt/settings.py
quickstats/algorithms/nll_crossing/BaseMethod.py
quickstats/algorithms/nll_crossing/BisectionMethod.py
quickstats/algorithms/nll_crossing/NovelMethod.py
quickstats/algorithms/nll_crossing/SteppingMethod.py
quickstats/algorithms/nll_crossing/__init__.py
quickstats/analysis/__init__.py
quickstats/analysis/analysis_base.py
quickstats/analysis/analysis_path_manager.py
quickstats/analysis/config_templates.py
quickstats/analysis/data_loading.py
quickstats/analysis/data_preprocessing.py
quickstats/analysis/event_categorization.py
quickstats/analysis/multi_class_boundary_tree.py
quickstats/analysis/ntuple_conversion_tool.py
quickstats/analysis/ntuple_process_tool.py
quickstats/analysis/sample_poly_param_tool.py
quickstats/analysis/systematics/__init__.py
quickstats/analysis/systematics/base_systematics.py
quickstats/analysis/systematics/gaussian_shape_systematics.py
quickstats/analysis/systematics/normalization_systematics.py
quickstats/analysis/systematics/systematics_evaluation_tool_deprecated.py
quickstats/clis/__init__.py
quickstats/clis/core.py
quickstats/clis/inspect_rfile.py
quickstats/clis/likelihood_tools.py
quickstats/clis/limit_setting.py
quickstats/clis/nuisance_parameter_tools.py
quickstats/clis/processor_tools.py
quickstats/clis/stat_tools.py
quickstats/clis/workspace_tools.py
quickstats/components/__init__.py
quickstats/components/analysis_base.py
quickstats/components/analysis_object.py
quickstats/components/asimov_generator.py
quickstats/components/asymptotic_cls.py
quickstats/components/basics.py
quickstats/components/caching_nll_wrapper.py
quickstats/components/discrete_nuisance.py
quickstats/components/extended_minimizer.py
quickstats/components/extended_model.py
quickstats/components/extended_rfile.py
quickstats/components/likelihood.py
quickstats-0.8.4.0.dist-info/licenses/LICENSE
quickstats-0.8.4.0.dist-info/METADATA
quickstats-0.8.4.0.dist-info/WHEEL
quickstats-0.8.4.0.dist-info/top_level.txt
quickstats-0.8.4.0.dist-info/RECORD
