Metadata-Version: 2.4
Name: quickstats
Version: 0.8.4.0
Summary: A tool for quick statistical analysis for HEP experiments
Author: Alkaid Cheng
Author-email: chi.lung.cheng@cern.ch
Classifier: Programming Language :: Python :: 3.7
Classifier: Programming Language :: Python :: 3.8
Classifier: License :: OSI Approved :: MIT License
Classifier: Operating System :: OS Independent
Requires-Python: >=3.7
License-File: LICENSE
Requires-Dist: numpy
Requires-Dist: matplotlib
Requires-Dist: click
Requires-Dist: pandas
Requires-Dist: tabulate
Requires-Dist: PyYAML
Requires-Dist: typing_extensions
Dynamic: author
Dynamic: author-email
Dynamic: classifier
Dynamic: description
Dynamic: description-content-type
Dynamic: license-file
Dynamic: requires-dist
Dynamic: requires-python
Dynamic: summary
